qwen_cpp/_C.cpython-310-darwin.so
qwen_cpp/__init__.py
qwen_cpp/convert.py
tiktoken_cpp/__init__.py
tiktoken_cpp/core.py
tiktoken_cpp/load.py
tiktoken_cpp/model.py
tiktoken_cpp/registry.py
qwen_cpp-0.1.2.dist-info/LICENSE
qwen_cpp-0.1.2.dist-info/METADATA
qwen_cpp-0.1.2.dist-info/NOTICE
qwen_cpp-0.1.2.dist-info/WHEEL
qwen_cpp-0.1.2.dist-info/top_level.txt
qwen_cpp-0.1.2.dist-info/RECORD
