Metadata-Version: 2.1
Name: qwen-cpp
Version: 0.1.2
Summary: C++ implementation of qwen & tiktoken
Author: Shijie Wang
Author-email: Shijie Wang <saimeng.wsj@alibaba-inc.com>
Maintainer-email: Shijie Wang <saimeng.wsj@alibaba-inc.com>
License: MIT License
Project-URL: Homepage, https://github.com/QwenLM/qwen.cpp
Project-URL: Repository, https://github.com/QwenLM/qwen.cpp.git
Project-URL: BugTracker, https://github.com/QwenLM/qwen.cpp/issues
Keywords: qwen,tiktoken
Classifier: Development Status :: 3 - Alpha
Classifier: Intended Audience :: Science/Research
Classifier: Topic :: Scientific/Engineering :: Artificial Intelligence
Classifier: License :: OSI Approved :: MIT License
Classifier: Programming Language :: Python :: 3.8
Classifier: Programming Language :: Python :: 3.9
Classifier: Programming Language :: Python :: 3.10
Classifier: Programming Language :: Python :: 3.11
Requires-Python: >=3.7
License-File: LICENSE
License-File: NOTICE
